datadump/__init__.py
datadump/datadump.py
datadump-0.0.1.dist-info/DESCRIPTION.rst
datadump-0.0.1.dist-info/METADATA
datadump-0.0.1.dist-info/RECORD
datadump-0.0.1.dist-info/WHEEL
datadump-0.0.1.dist-info/metadata.json
datadump-0.0.1.dist-info/top_level.txt
