Metadata-Version: 2.0
Name: datadump
Version: 0.0.1
Summary: Organized workspaces for simple saving and loading of variables
Home-page: https://github.com/riceric22/datadump
Author: Eric Wong
Author-email: ericwong@cs.cmu.edu
License: Apache 2.0
Platform: any
